[
  {
    "student_id": "Ayaan_Mishra_27",
    "student_name": "Ayaan Mishra",
    "roll_number": "27",
    "marks": 50,
    "report_path": "reports\\Ayaan_Mishra_27.pdf"
  },
  {
    "student_id": "Rajiv_Patel_29",
    "student_name": "Rajiv Patel",
    "roll_number": "29",
    "marks": 44,
    "report_path": "reports\\Rajiv_Patel_29.pdf"
  },
  {
    "student_id": "Rajesh_Kumar_14",
    "student_name": "Rajesh Kumar",
    "roll_number": "14",
    "marks": 34,
    "report_path": "reports\\Rajesh_Kumar_14.pdf"
  },
  {
    "student_id": "Sanjiv_Bansal_15",
    "student_name": "Sanjiv Bansal",
    "roll_number": "15",
    "marks": 24,
    "report_path": "reports\\Sanjiv_Bansal_15.pdf"
  }
]